MANIFEST.in
README.md
setup.py
bin/django_wsgi_deploy
django_wsgi_deployer/__init__.py
django_wsgi_deployer.egg-info/PKG-INFO
django_wsgi_deployer.egg-info/SOURCES.txt
django_wsgi_deployer.egg-info/dependency_links.txt
django_wsgi_deployer.egg-info/requires.txt
django_wsgi_deployer.egg-info/top_level.txt