Metadata-Version: 1.1
Name: django-wsgi-deployer
Version: 0.3.3
Summary: Django WSGI Project Deployer
Home-page: https://github.com/evili/django_wsgi_deployer
Author: Evili del Rio
Author-email: evili.del.rio@gmail.com
License: LGPL
Keywords: django wsgi apache deployment
Platform: UNKNOWN
Classifier: Development Status :: 4 - Beta
Classifier: Environment :: Console
Classifier: Framework :: Django
Classifier: Intended Audience :: Developers
Classifier: Intended Audience :: System Administrators
Classifier: License :: OSI Approved :: GNU Library or Lesser General Public License (LGPL)
Classifier: Natural Language :: English
Classifier: Operating System :: POSIX
Classifier: Programming Language :: Python
Classifier: Topic :: Internet :: WWW/HTTP :: WSGI
Classifier: Topic :: Utilities
